flipflop/src/edge.v
module edge_mod(
input clk,
input rstn,
input cin,
output cout
);

reg cin_1;
//initially this was not here
reg cin_2;
reg cin_3;
reg cin_4;


always @(posedge clk or negedge rstn)
begin
 if(~rstn)
  begin
   cin_1 <= 1'b0;
   cin_2 <= 1'b0;
   cin_3 <= 1'b0;
   cin_4 <= 1'b0;
  end
 else
  begin
   //cin_f <= cin;
   cin_1 <= cin;
   cin_2 <= cin_1;
   cin_3 <= cin_2;
   cin_4 <= cin_3;
  end
end

//initally it was assign_count = cin_f;
assign cout = cin_4 & ~cin_3 & cin_2 & cin_1;

endmodule

flipflop/tb/edge_tb.v
module edge_tb;
reg clk,rstn;
reg cin;
wire cout;

edge_mod dut0(.clk(clk),.rstn(rstn),.cin(cin),.cout(cout));

initial
begin
 clk = 0;
 forever #5 clk = ~clk;
end

initial
begin
 $dumpfile("edge.vcd");
 $dumpvars(0,edge_tb);
 
 rstn=0; cin=0; #20; rstn =1;
 #500; cin=1;
 #500; cin=1;
 @(posedge clk); #1;
 cin=0;
 @(posedge clk); #1;
 cin=1;
 @(posedge clk); #1;
 cin=1;

 #5000;
 $display("\n*********FINISHING********\n");
 $finish;

end
endmodule

flipflop/edge.vcd
$date
	Sun Mar  1 13:06:18 2020
$end
$version
	Icarus Verilog
$end
$timescale
	1s
$end
$scope module edge_tb $end
$var wire 1 ! cout $end
$var reg 1 " cin $end
$var reg 1 # clk $end
$var reg 1 $ rstn $end
$scope module dut0 $end
$var wire 1 " cin $end
$var wire 1 # clk $end
$var wire 1 ! cout $end
$var wire 1 $ rstn $end
$var reg 1 % cin_1 $end
$var reg 1 & cin_2 $end
$var reg 1 ' cin_3 $end
$var reg 1 ( cin_4 $end
$upscope $end
$upscope $end
$enddefinitions $end
#0
$dumpvars
0(
0'
0&
0%
0$
0#
0"
0!
$end
#5
1#
#10
0#
#15
1#
#20
0#
1$
#25
1#
#30
0#
#35
1#
#40
0#
#45
1#
#50
0#
#55
1#
#60
0#
#65
1#
#70
0#
#75
1#
#80
0#
#85
1#
#90
0#
#95
1#
#100
0#
#105
1#
#110
0#
#115
1#
#120
0#
#125
1#
#130
0#
#135
1#
#140
0#
#145
1#
#150
0#
#155
1#
#160
0#
#165
1#
#170
0#
#175
1#
#180
0#
#185
1#
#190
0#
#195
1#
#200
0#
#205
1#
#210
0#
#215
1#
#220
0#
#225
1#
#230
0#
#235
1#
#240
0#
#245
1#
#250
0#
#255
1#
#260
0#
#265
1#
#270
0#
#275
1#
#280
0#
#285
1#
#290
0#
#295
1#
#300
0#
#305
1#
#310
0#
#315
1#
#320
0#
#325
1#
#330
0#
#335
1#
#340
0#
#345
1#
#350
0#
#355
1#
#360
0#
#365
1#
#370
0#
#375
1#
#380
0#
#385
1#
#390
0#
#395
1#
#400
0#
#405
1#
#410
0#
#415
1#
#420
0#
#425
1#
#430
0#
#435
1#
#440
0#
#445
1#
#450
0#
#455
1#
#460
0#
#465
1#
#470
0#
#475
1#
#480
0#
#485
1#
#490
0#
#495
1#
#500
0#
#505
1#
#510
0#
#515
1#
#520
0#
1"
#525
1%
1#
#530
0#
#535
1&
1#
#540
0#
#545
1'
1#
#550
0#
#555
1(
1#
#560
0#
#565
1#
#570
0#
#575
1#
#580
0#
#585
1#
#590
0#
#595
1#
#600
0#
#605
1#
#610
0#
#615
1#
#620
0#
#625
1#
#630
0#
#635
1#
#640
0#
#645
1#
#650
0#
#655
1#
#660
0#
#665
1#
#670
0#
#675
1#
#680
0#
#685
1#
#690
0#
#695
1#
#700
0#
#705
1#
#710
0#
#715
1#
#720
0#
#725
1#
#730
0#
#735
1#
#740
0#
#745
1#
#750
0#
#755
1#
#760
0#
#765
1#
#770
0#
#775
1#
#780
0#
#785
1#
#790
0#
#795
1#
#800
0#
#805
1#
#810
0#
#815
1#
#820
0#
#825
1#
#830
0#
#835
1#
#840
0#
#845
1#
#850
0#
#855
1#
#860
0#
#865
1#
#870
0#
#875
1#
#880
0#
#885
1#
#890
0#
#895
1#
#900
0#
#905
1#
#910
0#
#915
1#
#920
0#
#925
1#
#930
0#
#935
1#
#940
0#
#945
1#
#950
0#
#955
1#
#960
0#
#965
1#
#970
0#
#975
1#
#980
0#
#985
1#
#990
0#
#995
1#
#1000
0#
#1005
1#
#1010
0#
#1015
1#
#1020
0#
#1025
1#
#1026
0"
#1030
0#
#1035
0%
1#
#1036
1"
#1040
0#
#1045
0&
1%
1#
#1050
0#
#1055
1!
0'
1&
1#
#1060
0#
#1065
0!
0(
1'
1#
#1070
0#
#1075
1(
1#
